allyourbase/__init__.py
allyourbase/base_convert.py
allyourbase/large_base_number.py
allyourbase/number_representation.py
allyourbase/standard_number.py
allyourbase-1.0.0.dist-info/DESCRIPTION.rst
allyourbase-1.0.0.dist-info/METADATA
allyourbase-1.0.0.dist-info/metadata.json
allyourbase-1.0.0.dist-info/RECORD
allyourbase-1.0.0.dist-info/top_level.txt
allyourbase-1.0.0.dist-info/WHEEL
