Metadata-Version: 1.1
Name: allyourbase
Version: 1.0.0
Summary: Numerical base converter, allowing arbitrary floating point precision and conversion between any integer bases
Home-page: https://bitbucket.org/birnam/allyourbase
Author: David Woods
Author-email: d@vidwoods.com
License: MIT
Keywords: base radix conversion convert float precision
Platform: UNKNOWN
Classifier: Development Status :: 4 - Beta
Classifier: Intended Audience :: Developers
Classifier: Intended Audience :: Science/Research
Classifier: Topic :: Scientific/Engineering :: Mathematics
Classifier: License :: OSI Approved :: MIT License
Classifier: Programming Language :: Python :: 3
Classifier: Programming Language :: Python :: 3.2
Classifier: Programming Language :: Python :: 3.3
Classifier: Programming Language :: Python :: 3.4
